fractal_network/NetworkGenerator.py
fractal_network/__init__.py
hierarchicalnet/NetworkGenerator.py
hierarchicalnet/__init__.py
fractal_network-0.0.2.dist-info/LICENSE
fractal_network-0.0.2.dist-info/METADATA
fractal_network-0.0.2.dist-info/WHEEL
fractal_network-0.0.2.dist-info/top_level.txt
fractal_network-0.0.2.dist-info/RECORD
