Metadata-Version: 2.1
Name: fractal-network
Version: 0.0.2
Summary: Creating fractal networks
Home-page: https://github.com/pypa/sampleproject
Author: Kimmo
Author-email: kimmo.kaski@aalto.fi
License: UNKNOWN
Project-URL: Bug Tracker, https://github.com/pypa/sampleproject/issues
Platform: UNKNOWN
Classifier: Programming Language :: Python :: 3
Classifier: License :: OSI Approved :: MIT License
Classifier: Operating System :: OS Independent
Requires-Python: >=3.6
